dicee/__init__.py
dicee/__main__.py
dicee/abstracts.py
dicee/analyse_experiments.py
dicee/callbacks.py
dicee/config.py
dicee/dataset_classes.py
dicee/eval_static_funcs.py
dicee/evaluator.py
dicee/executer.py
dicee/knowledge_graph.py
dicee/knowledge_graph_embeddings.py
dicee/query_generator.py
dicee/sanity_checkers.py
dicee/static_funcs.py
dicee/static_funcs_training.py
dicee/static_preprocess_funcs.py
dicee/weight_averaging.py
dicee/evaluation/__init__.py
dicee/evaluation/ensemble.py
dicee/evaluation/evaluator.py
dicee/evaluation/link_prediction.py
dicee/evaluation/literal_prediction.py
dicee/evaluation/utils.py
dicee/models/__init__.py
dicee/models/adopt.py
dicee/models/base_model.py
dicee/models/clifford.py
dicee/models/complex.py
dicee/models/dualE.py
dicee/models/ensemble.py
dicee/models/function_space.py
dicee/models/literal.py
dicee/models/octonion.py
dicee/models/pykeen_models.py
dicee/models/quaternion.py
dicee/models/real.py
dicee/models/static_funcs.py
dicee/models/transformers.py
dicee/read_preprocess_save_load_kg/__init__.py
dicee/read_preprocess_save_load_kg/preprocess.py
dicee/read_preprocess_save_load_kg/read_from_disk.py
dicee/read_preprocess_save_load_kg/save_load_disk.py
dicee/read_preprocess_save_load_kg/util.py
dicee/scripts/__init__.py
dicee/scripts/index_serve.py
dicee/scripts/run.py
dicee/trainer/__init__.py
dicee/trainer/dice_trainer.py
dicee/trainer/model_parallelism.py
dicee/trainer/torch_trainer.py
dicee/trainer/torch_trainer_ddp.py
dicee-0.3.1.dist-info/licenses/LICENSE
dicee-0.3.1.dist-info/METADATA
dicee-0.3.1.dist-info/WHEEL
dicee-0.3.1.dist-info/entry_points.txt
dicee-0.3.1.dist-info/top_level.txt
dicee-0.3.1.dist-info/RECORD
