Metadata-Version: 2.4
Name: dicee
Version: 0.3.1
Summary: Dice embedding is an hardware-agnostic framework for large-scale knowledge graph embedding applications
Home-page: https://github.com/dice-group/dice-embeddings
Author: Caglar Demir
Author-email: caglardemir8@gmail.com
Classifier: Programming Language :: Python :: 3.11
Classifier: License :: OSI Approved :: MIT License
Requires-Python: >=3.11
License-File: LICENSE
Requires-Dist: numpy==1.26.4
Requires-Dist: torch>=2.5.1
Requires-Dist: lightning>=2.5.0.post0
Requires-Dist: pandas>=2.1.0
Requires-Dist: requests>=2.32.3
Requires-Dist: polars>=0.16.14
Requires-Dist: pytorch_lightning>=2.5.1
Requires-Dist: tiktoken>=0.5.1
Provides-Extra: min
Requires-Dist: numpy==1.26.4; extra == "min"
Requires-Dist: torch>=2.5.1; extra == "min"
Requires-Dist: lightning>=2.5.0.post0; extra == "min"
Requires-Dist: pandas>=2.1.0; extra == "min"
Requires-Dist: requests>=2.32.3; extra == "min"
Requires-Dist: polars>=0.16.14; extra == "min"
Requires-Dist: pytorch_lightning>=2.5.1; extra == "min"
Requires-Dist: tiktoken>=0.5.1; extra == "min"
Provides-Extra: dev
Requires-Dist: numpy==1.26.4; extra == "dev"
Requires-Dist: torch>=2.5.1; extra == "dev"
Requires-Dist: lightning>=2.5.0.post0; extra == "dev"
Requires-Dist: pandas>=2.1.0; extra == "dev"
Requires-Dist: requests>=2.32.3; extra == "dev"
Requires-Dist: polars>=0.16.14; extra == "dev"
Requires-Dist: pytorch_lightning>=2.5.1; extra == "dev"
Requires-Dist: tiktoken>=0.5.1; extra == "dev"
Requires-Dist: pyarrow>=11.0.0; extra == "dev"
Requires-Dist: rdflib>=7.0.0; extra == "dev"
Requires-Dist: tiktoken>=0.5.1; extra == "dev"
Requires-Dist: pykeen>=1.10.2; extra == "dev"
Requires-Dist: psutil>=5.9.4; extra == "dev"
Requires-Dist: matplotlib>=3.8.2; extra == "dev"
Requires-Dist: zstandard>=0.21.0; extra == "dev"
Requires-Dist: requests>=2.32.3; extra == "dev"
Requires-Dist: scikit-learn>=1.2.2; extra == "dev"
Requires-Dist: pytest>=7.2.2; extra == "dev"
Requires-Dist: ruff>=0.0.284; extra == "dev"
Requires-Dist: scikit-learn>=1.2.2; extra == "dev"
Provides-Extra: docs
Requires-Dist: sphinx>=7.2.6; extra == "docs"
Requires-Dist: sphinx-autoapi>=3.0.0; extra == "docs"
Requires-Dist: myst-parser>=2.0.0; extra == "docs"
Requires-Dist: sphinx_rtd_theme>=2.0.0; extra == "docs"
Requires-Dist: sphinx-theme>=1.0; extra == "docs"
Requires-Dist: sphinxcontrib-plantuml>=0.27; extra == "docs"
Requires-Dist: plantuml-local-client>=1.2022.6; extra == "docs"
Provides-Extra: all
Requires-Dist: numpy==1.26.4; extra == "all"
Requires-Dist: torch>=2.5.1; extra == "all"
Requires-Dist: lightning>=2.5.0.post0; extra == "all"
Requires-Dist: pandas>=2.1.0; extra == "all"
Requires-Dist: requests>=2.32.3; extra == "all"
Requires-Dist: polars>=0.16.14; extra == "all"
Requires-Dist: pytorch_lightning>=2.5.1; extra == "all"
Requires-Dist: tiktoken>=0.5.1; extra == "all"
Requires-Dist: pyarrow>=11.0.0; extra == "all"
Requires-Dist: rdflib>=7.0.0; extra == "all"
Requires-Dist: tiktoken>=0.5.1; extra == "all"
Requires-Dist: pykeen>=1.10.2; extra == "all"
Requires-Dist: psutil>=5.9.4; extra == "all"
Requires-Dist: matplotlib>=3.8.2; extra == "all"
Requires-Dist: zstandard>=0.21.0; extra == "all"
Requires-Dist: requests>=2.32.3; extra == "all"
Requires-Dist: scikit-learn>=1.2.2; extra == "all"
Requires-Dist: pytest>=7.2.2; extra == "all"
Requires-Dist: ruff>=0.0.284; extra == "all"
Requires-Dist: scikit-learn>=1.2.2; extra == "all"
Requires-Dist: sphinx>=7.2.6; extra == "all"
Requires-Dist: sphinx-autoapi>=3.0.0; extra == "all"
Requires-Dist: myst-parser>=2.0.0; extra == "all"
Requires-Dist: sphinx_rtd_theme>=2.0.0; extra == "all"
Requires-Dist: sphinx-theme>=1.0; extra == "all"
Requires-Dist: sphinxcontrib-plantuml>=0.27; extra == "all"
Requires-Dist: plantuml-local-client>=1.2022.6; extra == "all"
Dynamic: author
Dynamic: author-email
Dynamic: classifier
Dynamic: description
Dynamic: description-content-type
Dynamic: home-page
Dynamic: license-file
Dynamic: provides-extra
Dynamic: requires-dist
Dynamic: requires-python
Dynamic: summary
